writer_pdf/__init__.py
writer_pdf/writer_pdf.py
writer_pdf-0.3.3.dist-info/licenses/LICENSE
writer_pdf-0.3.3.dist-info/METADATA
writer_pdf-0.3.3.dist-info/WHEEL
writer_pdf-0.3.3.dist-info/top_level.txt
writer_pdf-0.3.3.dist-info/RECORD
