Metadata-Version: 2.4
Name: writer-pdf
Version: 0.3.3
Summary: A simple Python library for creating and modifying PDF documents.
Author-email: "xb.g" <2322405760@qq.com>
License: MIT
Classifier: Programming Language :: Python :: 3
Classifier: License :: OSI Approved :: MIT License
Classifier: Operating System :: OS Independent
Classifier: Topic :: Software Development :: Libraries :: Python Modules
Classifier: Topic :: Multimedia :: Graphics
Requires-Python: >=3.8
License-File: LICENSE
Requires-Dist: reportlab>=3.5.0
Requires-Dist: PyPDF2>=1.27.0
Dynamic: license-file
